[
	{
		"__TYPE__": "SharedSliceContent",
		"variation": "default",
		"primary": {
			"title": {
				"__TYPE__": "StructuredTextContent",
				"value": [
					{
						"type": "heading1",
						"content": {
							"text": "Caught"
						}
					}
				]
			},
			"subtitle": {
				"__TYPE__": "StructuredTextContent",
				"value": [
					{
						"type": "paragraph",
						"content": {
							"text": "Sit elit exercitation officia. Ea esse dolore ad."
						}
					}
				]
			},
			"backgroundImage": {
				"origin": {
					"id": "main",
					"url": "https://images.unsplash.com/photo-1494173853739-c21f58b16055",
					"width": 3277,
					"height": 4092
				},
				"url": "https://images.unsplash.com/photo-1494173853739-c21f58b16055?rect=0%2C1124%2C3277%2C1843&w=1920&h=1080",
				"width": 1920,
				"height": 1080,
				"edit": {
					"zoom": 1,
					"crop": {
						"x": 0,
						"y": 1124
					},
					"background": "transparent"
				},
				"alt": "poor",
				"credits": null,
				"__TYPE__": "ImageContent"
			},
			"footerText": {
				"__TYPE__": "StructuredTextContent",
				"value": [
					{
						"type": "paragraph",
						"content": {
							"text": "Ut do Lorem reprehenderit consectetur veniam incididunt sit reprehenderit ex aliquip aliqua quis veniam qui. Ea cillum sunt proident consequat esse do culpa in ea nostrud aute ullamco ut nostrud fugiat. Sint irure aliquip anim."
						}
					}
				]
			},
			"cta": {
				"key": "72131f72-450e-4301-a394-44d7b68783dc",
				"__TYPE__": "LinkContent",
				"value": {
					"__TYPE__": "ExternalLink",
					"url": "https://slicemachine.dev",
					"text": "necessary"
				}
			}
		},
		"items": []
	}
]